MANIFEST.in
README.rst
setup.cfg
setup.py
docs/LICENSE.GPL
docs/LICENSE.txt
seantis/.DS_Store
seantis/__init__.py
seantis.web.egg-info/PKG-INFO
seantis.web.egg-info/SOURCES.txt
seantis.web.egg-info/dependency_links.txt
seantis.web.egg-info/entry_points.txt
seantis.web.egg-info/namespace_packages.txt
seantis.web.egg-info/not-zip-safe
seantis.web.egg-info/requires.txt
seantis.web.egg-info/top_level.txt
seantis/web/.DS_Store
seantis/web/__init__.py
seantis/web/configure.zcml
seantis/web/interfaces.py
seantis/web/testing.py
seantis/web/portlets/__init__.py
seantis/web/portlets/archive.pt
seantis/web/portlets/archive.py
seantis/web/profiles/default/browserlayer.xml
seantis/web/profiles/default/metadata.xml
seantis/web/profiles/default/properties.xml
seantis/web/profiles/default/theme.xml
seantis/web/profiles/default/viewlets.xml
seantis/web/resources/.DS_Store
seantis/web/resources/favicon.ico
seantis/web/resources/manifest.cfg
seantis/web/resources/preview.png
seantis/web/resources/robots.txt
seantis/web/resources/rules.xml
seantis/web/resources/theme.html
seantis/web/resources/css/foundation.min.css
seantis/web/resources/css/main.css
seantis/web/resources/css/normalize.min.css
seantis/web/resources/css/prism.css
seantis/web/resources/img/.gitkeep
seantis/web/resources/img/display.jpg
seantis/web/resources/img/iphone-5.psd
seantis/web/resources/img/logo-path.ai
seantis/web/resources/img/logo.ai
seantis/web/resources/img/logo.png
seantis/web/resources/img/logo.svg
seantis/web/resources/img/medication.png
seantis/web/resources/img/news.png
seantis/web/resources/img/ocqm.png
seantis/web/resources/img/onegov.jpg
seantis/web/resources/img/onegov_big.jpg
seantis/web/resources/img/panorma.png
seantis/web/resources/img/portrait.png
seantis/web/resources/img/portrait.psd
seantis/web/resources/img/risch.png
seantis/web/resources/img/scqm.png
seantis/web/resources/ionicons/ionicons.min.css
seantis/web/resources/ionicons/fonts/ionicons.eot
seantis/web/resources/ionicons/fonts/ionicons.svg
seantis/web/resources/ionicons/fonts/ionicons.ttf
seantis/web/resources/ionicons/fonts/ionicons.woff
seantis/web/resources/js/custom.modernizr.js
seantis/web/resources/js/foundation.min.js
seantis/web/resources/js/main.js
seantis/web/resources/js/prism.js
