Metadata-Version: 1.1
Name: seantis.web
Version: 1.3.1
Summary: The seantis website.
Home-page: https://github.com/seantis/seantis.web
Author: Seantis GmbH
Author-email: info@seantis.ch
License: gpl
Keywords: plone seantis website
Platform: UNKNOWN
Classifier: Environment :: Web Environment
Classifier: Framework :: Plone
Classifier: Operating System :: OS Independent
Classifier: Programming Language :: Python
Classifier: Programming Language :: Python :: 2.6
Classifier: Topic :: Software Development :: Libraries :: Python Modules
